prnv/__init__.py
prnv/art.py
prnv/main.py
prnv-0.1.dist-info/LICENSE
prnv-0.1.dist-info/METADATA
prnv-0.1.dist-info/WHEEL
prnv-0.1.dist-info/entry_points.txt
prnv-0.1.dist-info/top_level.txt
prnv-0.1.dist-info/RECORD
